{
    "predict_GPE_f1": 0.7575965057254163,
    "predict_GPE_number": 20409,
    "predict_GPE_precision": 0.7310671648591999,
    "predict_GPE_recall": 0.7861237689254741,
    "predict_actor_f1": 0.6868099941894248,
    "predict_actor_number": 1638,
    "predict_actor_precision": 0.655210643015521,
    "predict_actor_recall": 0.7216117216117216,
    "predict_airplane_f1": 0.5477629987908101,
    "predict_airplane_number": 794,
    "predict_airplane_precision": 0.5267441860465116,
    "predict_airplane_recall": 0.570528967254408,
    "predict_airport_f1": 0.6420927467300833,
    "predict_airport_number": 364,
    "predict_airport_precision": 0.5660377358490566,
    "predict_airport_recall": 0.7417582417582418,
    "predict_artist/author_f1": 0.597452934662237,
    "predict_artist/author_number": 3464,
    "predict_artist/author_precision": 0.573936170212766,
    "predict_artist/author_recall": 0.6229792147806005,
    "predict_astronomything_f1": 0.6475570032573289,
    "predict_astronomything_number": 678,
    "predict_astronomything_precision": 0.5799299883313885,
    "predict_astronomything_recall": 0.7330383480825958,
    "predict_athlete_f1": 0.7811301883647275,
    "predict_athlete_number": 2907,
    "predict_athlete_precision": 0.7577619663648124,
    "predict_athlete_recall": 0.8059855521155831,
    "predict_attack/battle/war/militaryconflict_f1": 0.601010101010101,
    "predict_attack/battle/war/militaryconflict_number": 1099,
    "predict_attack/battle/war/militaryconflict_precision": 0.5591229444009397,
    "predict_attack/battle/war/militaryconflict_recall": 0.6496815286624203,
    "predict_award_f1": 0.41395568128241395,
    "predict_award_number": 941,
    "predict_award_precision": 0.37203389830508476,
    "predict_award_recall": 0.4665249734325186,
    "predict_biologything_f1": 0.5362003266194882,
    "predict_biologything_number": 1875,
    "predict_biologything_precision": 0.547526403557532,
    "predict_biologything_recall": 0.5253333333333333,
    "predict_bodiesofwater_f1": 0.6173913043478262,
    "predict_bodiesofwater_number": 1169,
    "predict_bodiesofwater_precision": 0.5738427626745041,
    "predict_bodiesofwater_recall": 0.6680923866552609,
    "predict_broadcastprogram_f1": 0.4493783303730018,
    "predict_broadcastprogram_number": 605,
    "predict_broadcastprogram_precision": 0.4856046065259117,
    "predict_broadcastprogram_recall": 0.41818181818181815,
    "predict_car_f1": 0.5949554896142433,
    "predict_car_number": 688,
    "predict_car_precision": 0.6075757575757575,
    "predict_car_recall": 0.5828488372093024,
    "predict_chemicalthing_f1": 0.48396264717823795,
    "predict_chemicalthing_number": 1014,
    "predict_chemicalthing_precision": 0.4113181504485852,
    "predict_chemicalthing_recall": 0.5877712031558185,
    "predict_company_f1": 0.5632994620442319,
    "predict_company_number": 3903,
    "predict_company_precision": 0.528014343343792,
    "predict_company_recall": 0.603638227004868,
    "predict_currency_f1": 0.6586620926243568,
    "predict_currency_number": 799,
    "predict_currency_precision": 0.6063157894736843,
    "predict_currency_recall": 0.72090112640801,
    "predict_director_f1": 0.5916149068322981,
    "predict_director_number": 554,
    "predict_director_precision": 0.5190735694822888,
    "predict_director_recall": 0.6877256317689531,
    "predict_disaster_f1": 0.3726235741444867,
    "predict_disaster_number": 207,
    "predict_disaster_precision": 0.3072100313479624,
    "predict_disaster_recall": 0.47342995169082125,
    "predict_disease_f1": 0.5250836120401338,
    "predict_disease_number": 750,
    "predict_disease_precision": 0.4511494252873563,
    "predict_disease_recall": 0.628,
    "predict_education_f1": 0.6362410071942446,
    "predict_education_number": 2082,
    "predict_education_precision": 0.5980557903634827,
    "predict_education_recall": 0.6796349663784822,
    "predict_educationaldegree_f1": 0.37485970819304154,
    "predict_educationaldegree_number": 367,
    "predict_educationaldegree_precision": 0.3187022900763359,
    "predict_educationaldegree_recall": 0.4550408719346049,
    "predict_election_f1": 0.13333333333333333,
    "predict_election_number": 184,
    "predict_election_precision": 0.11278195488721804,
    "predict_election_recall": 0.16304347826086957,
    "predict_film_f1": 0.6218487394957983,
    "predict_film_number": 759,
    "predict_film_precision": 0.5711135611907387,
    "predict_film_recall": 0.6824769433465085,
    "predict_food_f1": 0.4224489795918368,
    "predict_food_number": 432,
    "predict_food_precision": 0.3777372262773723,
    "predict_food_recall": 0.4791666666666667,
    "predict_game_f1": 0.584771573604061,
    "predict_game_number": 496,
    "predict_game_precision": 0.588957055214724,
    "predict_game_recall": 0.5806451612903226,
    "predict_god_f1": 0.5320056899004267,
    "predict_god_number": 635,
    "predict_god_precision": 0.48508430609597925,
    "predict_god_recall": 0.5889763779527559,
    "predict_government/governmentagency_f1": 0.2933744221879815,
    "predict_government/governmentagency_number": 1535,
    "predict_government/governmentagency_precision": 0.2783625730994152,
    "predict_government/governmentagency_recall": 0.31009771986970686,
    "predict_hospital_f1": 0.5801324503311257,
    "predict_hospital_number": 364,
    "predict_hospital_precision": 0.5601023017902813,
    "predict_hospital_recall": 0.6016483516483516,
    "predict_hotel_f1": 0.5282392026578072,
    "predict_hotel_number": 265,
    "predict_hotel_precision": 0.47181008902077154,
    "predict_hotel_recall": 0.6,
    "predict_island_f1": 0.5182049110922947,
    "predict_island_number": 646,
    "predict_island_precision": 0.5719626168224299,
    "predict_island_recall": 0.47368421052631576,
    "predict_language_f1": 0.6501809408926418,
    "predict_language_number": 753,
    "predict_language_precision": 0.5955801104972376,
    "predict_language_recall": 0.7158034528552457,
    "predict_law_f1": 0.42065009560229444,
    "predict_law_number": 488,
    "predict_law_precision": 0.3942652329749104,
    "predict_law_recall": 0.45081967213114754,
    "predict_library_f1": 0.5955786736020807,
    "predict_library_number": 357,
    "predict_library_precision": 0.5558252427184466,
    "predict_library_recall": 0.6414565826330533,
    "predict_livingthing_f1": 0.5009469696969697,
    "predict_livingthing_number": 865,
    "predict_livingthing_precision": 0.4242181234963913,
    "predict_livingthing_recall": 0.6115606936416185,
    "predict_loss": 0.5015304684638977,
    "predict_media/newspaper_f1": 0.5226939970717422,
    "predict_media/newspaper_number": 1234,
    "predict_media/newspaper_precision": 0.4766355140186916,
    "predict_media/newspaper_recall": 0.5786061588330632,
    "predict_medical_f1": 0.3253182461103253,
    "predict_medical_number": 397,
    "predict_medical_precision": 0.3709677419354839,
    "predict_medical_recall": 0.28967254408060455,
    "predict_mountain_f1": 0.5400843881856541,
    "predict_mountain_number": 681,
    "predict_mountain_precision": 0.5182186234817814,
    "predict_mountain_recall": 0.5638766519823789,
    "predict_music_f1": 0.6264949402023919,
    "predict_music_number": 1041,
    "predict_music_precision": 0.6010591350397175,
    "predict_music_recall": 0.654178674351585,
    "predict_other_f1": 0.4573839291599833,
    "predict_other_number": 21035,
    "predict_other_precision": 0.4252328811897369,
    "predict_other_recall": 0.49479439030187783,
    "predict_overall_accuracy": 0.9040175711738943,
    "predict_overall_f1": 0.5709534260879654,
    "predict_overall_precision": 0.5370218802859169,
    "predict_overall_recall": 0.6094620814927961,
    "predict_painting_f1": 0.18604651162790697,
    "predict_painting_number": 58,
    "predict_painting_precision": 0.2857142857142857,
    "predict_painting_recall": 0.13793103448275862,
    "predict_park_f1": 0.4406091370558375,
    "predict_park_number": 458,
    "predict_park_precision": 0.4117647058823529,
    "predict_park_recall": 0.4737991266375546,
    "predict_politicalparty_f1": 0.5609965635738831,
    "predict_politicalparty_number": 1057,
    "predict_politicalparty_precision": 0.5137686860739575,
    "predict_politicalparty_recall": 0.6177861873226111,
    "predict_politician_f1": 0.5402436931525656,
    "predict_politician_number": 2859,
    "predict_politician_precision": 0.5303234501347709,
    "predict_politician_recall": 0.5505421476040574,
    "predict_protest_f1": 0.1774744027303754,
    "predict_protest_number": 166,
    "predict_protest_precision": 0.2047244094488189,
    "predict_protest_recall": 0.1566265060240964,
    "predict_religion_f1": 0.42659279778393355,
    "predict_religion_number": 676,
    "predict_religion_precision": 0.4010416666666667,
    "predict_religion_recall": 0.4556213017751479,
    "predict_restaurant_f1": 0.3691148775894539,
    "predict_restaurant_number": 232,
    "predict_restaurant_precision": 0.3277591973244147,
    "predict_restaurant_recall": 0.4224137931034483,
    "predict_road/railway/highway/transit_f1": 0.5705944798301485,
    "predict_road/railway/highway/transit_number": 1702,
    "predict_road/railway/highway/transit_precision": 0.5203291384317522,
    "predict_road/railway/highway/transit_recall": 0.6316098707403055,
    "predict_runtime": 290.9595,
    "predict_samples_per_second": 129.389,
    "predict_scholar_f1": 0.35480093676814994,
    "predict_scholar_number": 743,
    "predict_scholar_precision": 0.3139896373056995,
    "predict_scholar_recall": 0.4078061911170929,
    "predict_ship_f1": 0.48802736602052454,
    "predict_ship_number": 380,
    "predict_ship_precision": 0.4305835010060362,
    "predict_ship_recall": 0.5631578947368421,
    "predict_showorganization_f1": 0.4414796846573681,
    "predict_showorganization_number": 770,
    "predict_showorganization_precision": 0.4141069397042093,
    "predict_showorganization_recall": 0.4727272727272727,
    "predict_software_f1": 0.5157159487776485,
    "predict_software_number": 889,
    "predict_software_precision": 0.53437876960193,
    "predict_software_recall": 0.4983127109111361,
    "predict_soldier_f1": 0.4022114720110574,
    "predict_soldier_number": 647,
    "predict_soldier_precision": 0.36375,
    "predict_soldier_recall": 0.44976816074188564,
    "predict_sportsevent_f1": 0.4410876132930514,
    "predict_sportsevent_number": 1572,
    "predict_sportsevent_precision": 0.38811019816336395,
    "predict_sportsevent_recall": 0.5108142493638677,
    "predict_sportsfacility_f1": 0.567703109327984,
    "predict_sportsfacility_number": 420,
    "predict_sportsfacility_precision": 0.4904679376083189,
    "predict_sportsfacility_recall": 0.6738095238095239,
    "predict_sportsleague_f1": 0.468667719852554,
    "predict_sportsleague_number": 885,
    "predict_sportsleague_precision": 0.4388560157790927,
    "predict_sportsleague_recall": 0.5028248587570622,
    "predict_sportsteam_f1": 0.6571265025758444,
    "predict_sportsteam_number": 2477,
    "predict_sportsteam_precision": 0.6230101302460203,
    "predict_sportsteam_recall": 0.6951958013726282,
    "predict_steps_per_second": 4.045,
    "predict_theater_f1": 0.5724976613657624,
    "predict_theater_number": 456,
    "predict_theater_precision": 0.499184339314845,
    "predict_theater_recall": 0.6710526315789473,
    "predict_train_f1": 0.39544807965860596,
    "predict_train_number": 314,
    "predict_train_precision": 0.35732647814910024,
    "predict_train_recall": 0.4426751592356688,
    "predict_weapon_f1": 0.4478330658105939,
    "predict_weapon_number": 625,
    "predict_weapon_precision": 0.4492753623188406,
    "predict_weapon_recall": 0.4464,
    "predict_writtenart_f1": 0.4672897196261683,
    "predict_writtenart_number": 1032,
    "predict_writtenart_precision": 0.43209876543209874,
    "predict_writtenart_recall": 0.5087209302325582
}