{
    "predict_GPE_f1": 0.7330168679140934,
    "predict_GPE_number": 20409,
    "predict_GPE_precision": 0.691912820289729,
    "predict_GPE_recall": 0.7793130481650252,
    "predict_actor_f1": 0.5983510011778563,
    "predict_actor_number": 1638,
    "predict_actor_precision": 0.5779294653014789,
    "predict_actor_recall": 0.6202686202686203,
    "predict_airplane_f1": 0.4417989417989418,
    "predict_airplane_number": 794,
    "predict_airplane_precision": 0.46518105849582175,
    "predict_airplane_recall": 0.42065491183879095,
    "predict_airport_f1": 0.5264483627204031,
    "predict_airport_number": 364,
    "predict_airport_precision": 0.48604651162790696,
    "predict_airport_recall": 0.5741758241758241,
    "predict_artist/author_f1": 0.4919102651257648,
    "predict_artist/author_number": 3464,
    "predict_artist/author_precision": 0.46491904394757133,
    "predict_artist/author_recall": 0.5222286374133949,
    "predict_astronomything_f1": 0.5572005383580081,
    "predict_astronomything_number": 678,
    "predict_astronomything_precision": 0.5123762376237624,
    "predict_astronomything_recall": 0.6106194690265486,
    "predict_athlete_f1": 0.7242634889109566,
    "predict_athlete_number": 2907,
    "predict_athlete_precision": 0.6979266347687401,
    "predict_athlete_recall": 0.7526659786721707,
    "predict_attack/battle/war/militaryconflict_f1": 0.595460614152203,
    "predict_attack/battle/war/militaryconflict_number": 1099,
    "predict_attack/battle/war/militaryconflict_precision": 0.5827526132404182,
    "predict_attack/battle/war/militaryconflict_recall": 0.6087352138307552,
    "predict_award_f1": 0.4131054131054131,
    "predict_award_number": 941,
    "predict_award_precision": 0.37339055793991416,
    "predict_award_recall": 0.4622741764080765,
    "predict_biologything_f1": 0.5211372064276885,
    "predict_biologything_number": 1875,
    "predict_biologything_precision": 0.4857142857142857,
    "predict_biologything_recall": 0.5621333333333334,
    "predict_bodiesofwater_f1": 0.5366284201235658,
    "predict_bodiesofwater_number": 1169,
    "predict_bodiesofwater_precision": 0.5542388331814039,
    "predict_bodiesofwater_recall": 0.5201026518391788,
    "predict_broadcastprogram_f1": 0.3537117903930131,
    "predict_broadcastprogram_number": 605,
    "predict_broadcastprogram_precision": 0.3159947984395319,
    "predict_broadcastprogram_recall": 0.40165289256198344,
    "predict_car_f1": 0.5155420773313115,
    "predict_car_number": 688,
    "predict_car_precision": 0.5388272583201268,
    "predict_car_recall": 0.4941860465116279,
    "predict_chemicalthing_f1": 0.46221786064769377,
    "predict_chemicalthing_number": 1014,
    "predict_chemicalthing_precision": 0.4599609375,
    "predict_chemicalthing_recall": 0.46449704142011833,
    "predict_company_f1": 0.49721095334685594,
    "predict_company_number": 3903,
    "predict_company_precision": 0.4920953575909661,
    "predict_company_recall": 0.5024340251088906,
    "predict_currency_f1": 0.6526195899772209,
    "predict_currency_number": 799,
    "predict_currency_precision": 0.5987460815047022,
    "predict_currency_recall": 0.7171464330413017,
    "predict_director_f1": 0.4686695278969957,
    "predict_director_number": 554,
    "predict_director_precision": 0.44680851063829785,
    "predict_director_recall": 0.4927797833935018,
    "predict_disaster_f1": 0.34951456310679613,
    "predict_disaster_number": 207,
    "predict_disaster_precision": 0.2922077922077922,
    "predict_disaster_recall": 0.43478260869565216,
    "predict_disease_f1": 0.48780487804878053,
    "predict_disease_number": 750,
    "predict_disease_precision": 0.39408866995073893,
    "predict_disease_recall": 0.64,
    "predict_education_f1": 0.6107226107226108,
    "predict_education_number": 2082,
    "predict_education_precision": 0.5464543041334851,
    "predict_education_recall": 0.6921229586935639,
    "predict_educationaldegree_f1": 0.43995510662177334,
    "predict_educationaldegree_number": 367,
    "predict_educationaldegree_precision": 0.37404580152671757,
    "predict_educationaldegree_recall": 0.5340599455040872,
    "predict_election_f1": 0.13626373626373628,
    "predict_election_number": 184,
    "predict_election_precision": 0.11439114391143912,
    "predict_election_recall": 0.16847826086956522,
    "predict_film_f1": 0.489247311827957,
    "predict_film_number": 759,
    "predict_film_precision": 0.41326067211625794,
    "predict_film_recall": 0.5994729907773386,
    "predict_food_f1": 0.33216374269005844,
    "predict_food_number": 432,
    "predict_food_precision": 0.33569739952718675,
    "predict_food_recall": 0.3287037037037037,
    "predict_game_f1": 0.46778989098116946,
    "predict_game_number": 496,
    "predict_game_precision": 0.4600389863547758,
    "predict_game_recall": 0.47580645161290325,
    "predict_god_f1": 0.5026022304832714,
    "predict_god_number": 635,
    "predict_god_precision": 0.476056338028169,
    "predict_god_recall": 0.5322834645669291,
    "predict_government/governmentagency_f1": 0.30201532784558616,
    "predict_government/governmentagency_number": 1535,
    "predict_government/governmentagency_precision": 0.2676056338028169,
    "predict_government/governmentagency_recall": 0.3465798045602606,
    "predict_hospital_f1": 0.5374855824682813,
    "predict_hospital_number": 364,
    "predict_hospital_precision": 0.46322067594433397,
    "predict_hospital_recall": 0.6401098901098901,
    "predict_hotel_f1": 0.45990922844175497,
    "predict_hotel_number": 265,
    "predict_hotel_precision": 0.3838383838383838,
    "predict_hotel_recall": 0.5735849056603773,
    "predict_island_f1": 0.47153284671532847,
    "predict_island_number": 646,
    "predict_island_precision": 0.44613259668508287,
    "predict_island_recall": 0.5,
    "predict_language_f1": 0.6097560975609756,
    "predict_language_number": 753,
    "predict_language_precision": 0.5233111322549953,
    "predict_language_recall": 0.7304116865869854,
    "predict_law_f1": 0.41213202497769846,
    "predict_law_number": 488,
    "predict_law_precision": 0.36492890995260663,
    "predict_law_recall": 0.4733606557377049,
    "predict_library_f1": 0.45287637698898414,
    "predict_library_number": 357,
    "predict_library_precision": 0.40217391304347827,
    "predict_library_recall": 0.5182072829131653,
    "predict_livingthing_f1": 0.487957181088314,
    "predict_livingthing_number": 865,
    "predict_livingthing_precision": 0.3972403776325345,
    "predict_livingthing_recall": 0.6323699421965318,
    "predict_loss": 0.6758986711502075,
    "predict_media/newspaper_f1": 0.47388932190179267,
    "predict_media/newspaper_number": 1234,
    "predict_media/newspaper_precision": 0.45645645645645644,
    "predict_media/newspaper_recall": 0.49270664505672607,
    "predict_medical_f1": 0.3694412770809578,
    "predict_medical_number": 397,
    "predict_medical_precision": 0.3375,
    "predict_medical_recall": 0.4080604534005038,
    "predict_mountain_f1": 0.5205288796102993,
    "predict_mountain_number": 681,
    "predict_mountain_precision": 0.4947089947089947,
    "predict_mountain_recall": 0.5491923641703378,
    "predict_music_f1": 0.586063682510383,
    "predict_music_number": 1041,
    "predict_music_precision": 0.5639431616341031,
    "predict_music_recall": 0.6099903938520653,
    "predict_other_f1": 0.39699570815450647,
    "predict_other_number": 21035,
    "predict_other_precision": 0.37466773553858485,
    "predict_other_recall": 0.42215355360114093,
    "predict_overall_accuracy": 0.893606672355801,
    "predict_overall_f1": 0.523989363751975,
    "predict_overall_precision": 0.49130984643179765,
    "predict_overall_recall": 0.5613260124674896,
    "predict_painting_f1": 0.09917355371900828,
    "predict_painting_number": 58,
    "predict_painting_precision": 0.09523809523809523,
    "predict_painting_recall": 0.10344827586206896,
    "predict_park_f1": 0.3436619718309859,
    "predict_park_number": 458,
    "predict_park_precision": 0.3014827018121911,
    "predict_park_recall": 0.39956331877729256,
    "predict_politicalparty_f1": 0.545757071547421,
    "predict_politicalparty_number": 1057,
    "predict_politicalparty_precision": 0.48700816629547145,
    "predict_politicalparty_recall": 0.6206244087038789,
    "predict_politician_f1": 0.49755620723362654,
    "predict_politician_number": 2859,
    "predict_politician_precision": 0.4656907593778591,
    "predict_politician_recall": 0.534102833158447,
    "predict_protest_f1": 0.2216216216216216,
    "predict_protest_number": 166,
    "predict_protest_precision": 0.20098039215686275,
    "predict_protest_recall": 0.2469879518072289,
    "predict_religion_f1": 0.4124466137888957,
    "predict_religion_number": 676,
    "predict_religion_precision": 0.3509865005192108,
    "predict_religion_recall": 0.5,
    "predict_restaurant_f1": 0.25052192066805845,
    "predict_restaurant_number": 232,
    "predict_restaurant_precision": 0.242914979757085,
    "predict_restaurant_recall": 0.25862068965517243,
    "predict_road/railway/highway/transit_f1": 0.5163766632548618,
    "predict_road/railway/highway/transit_number": 1702,
    "predict_road/railway/highway/transit_precision": 0.457388939256573,
    "predict_road/railway/highway/transit_recall": 0.5928319623971798,
    "predict_runtime": 264.4002,
    "predict_samples_per_second": 142.386,
    "predict_scholar_f1": 0.31237042156185213,
    "predict_scholar_number": 743,
    "predict_scholar_precision": 0.3210227272727273,
    "predict_scholar_recall": 0.3041722745625841,
    "predict_ship_f1": 0.416058394160584,
    "predict_ship_number": 380,
    "predict_ship_precision": 0.38687782805429866,
    "predict_ship_recall": 0.45,
    "predict_showorganization_f1": 0.3322079675894666,
    "predict_showorganization_number": 770,
    "predict_showorganization_precision": 0.3459915611814346,
    "predict_showorganization_recall": 0.3194805194805195,
    "predict_software_f1": 0.41737032569360677,
    "predict_software_number": 889,
    "predict_software_precision": 0.44993498049414826,
    "predict_software_recall": 0.3892013498312711,
    "predict_soldier_f1": 0.3141891891891892,
    "predict_soldier_number": 647,
    "predict_soldier_precision": 0.3463687150837989,
    "predict_soldier_recall": 0.2874806800618238,
    "predict_sportsevent_f1": 0.412166003411029,
    "predict_sportsevent_number": 1572,
    "predict_sportsevent_precision": 0.3725590955806783,
    "predict_sportsevent_recall": 0.46119592875318066,
    "predict_sportsfacility_f1": 0.5348595213319459,
    "predict_sportsfacility_number": 420,
    "predict_sportsfacility_precision": 0.47504621072088726,
    "predict_sportsfacility_recall": 0.611904761904762,
    "predict_sportsleague_f1": 0.4645030425963489,
    "predict_sportsleague_number": 885,
    "predict_sportsleague_precision": 0.42134314627414904,
    "predict_sportsleague_recall": 0.5175141242937853,
    "predict_sportsteam_f1": 0.6006389776357828,
    "predict_sportsteam_number": 2477,
    "predict_sportsteam_precision": 0.5942315290399052,
    "predict_sportsteam_recall": 0.6071861122325394,
    "predict_steps_per_second": 4.452,
    "predict_theater_f1": 0.5379442843419789,
    "predict_theater_number": 456,
    "predict_theater_precision": 0.47863247863247865,
    "predict_theater_recall": 0.6140350877192983,
    "predict_train_f1": 0.33333333333333337,
    "predict_train_number": 314,
    "predict_train_precision": 0.29949238578680204,
    "predict_train_recall": 0.37579617834394907,
    "predict_weapon_f1": 0.4077961019490255,
    "predict_weapon_number": 625,
    "predict_weapon_precision": 0.383638928067701,
    "predict_weapon_recall": 0.4352,
    "predict_writtenart_f1": 0.3890784982935154,
    "predict_writtenart_number": 1032,
    "predict_writtenart_precision": 0.3475609756097561,
    "predict_writtenart_recall": 0.4418604651162791
}