{
    "predict_GPE_f1": 0.757690928648261,
    "predict_GPE_number": 20409,
    "predict_GPE_precision": 0.7397087650518063,
    "predict_GPE_recall": 0.7765691606644127,
    "predict_actor_f1": 0.6656822209096279,
    "predict_actor_number": 1638,
    "predict_actor_precision": 0.6447368421052632,
    "predict_actor_recall": 0.688034188034188,
    "predict_airplane_f1": 0.5332534451767525,
    "predict_airplane_number": 794,
    "predict_airplane_precision": 0.5085714285714286,
    "predict_airplane_recall": 0.5604534005037783,
    "predict_airport_f1": 0.5699067909454061,
    "predict_airport_number": 364,
    "predict_airport_precision": 0.5529715762273901,
    "predict_airport_recall": 0.5879120879120879,
    "predict_artist/author_f1": 0.5733262486716258,
    "predict_artist/author_number": 3464,
    "predict_artist/author_precision": 0.531003937007874,
    "predict_artist/author_recall": 0.6229792147806005,
    "predict_astronomything_f1": 0.6243691420331652,
    "predict_astronomything_number": 678,
    "predict_astronomything_precision": 0.610719322990127,
    "predict_astronomything_recall": 0.6386430678466076,
    "predict_athlete_f1": 0.7686604886267902,
    "predict_athlete_number": 2907,
    "predict_athlete_precision": 0.7533025099075297,
    "predict_athlete_recall": 0.7846577227382181,
    "predict_attack/battle/war/militaryconflict_f1": 0.6343537414965986,
    "predict_attack/battle/war/militaryconflict_number": 1099,
    "predict_attack/battle/war/militaryconflict_precision": 0.5953711093375897,
    "predict_attack/battle/war/militaryconflict_recall": 0.6787989080982711,
    "predict_award_f1": 0.46347363328495406,
    "predict_award_number": 941,
    "predict_award_precision": 0.42539964476021314,
    "predict_award_recall": 0.5090329436769394,
    "predict_biologything_f1": 0.5247601763028259,
    "predict_biologything_number": 1875,
    "predict_biologything_precision": 0.5105953582240161,
    "predict_biologything_recall": 0.5397333333333333,
    "predict_bodiesofwater_f1": 0.6001712328767124,
    "predict_bodiesofwater_number": 1169,
    "predict_bodiesofwater_precision": 0.6006855184233076,
    "predict_bodiesofwater_recall": 0.5996578272027374,
    "predict_broadcastprogram_f1": 0.4340836012861737,
    "predict_broadcastprogram_number": 605,
    "predict_broadcastprogram_precision": 0.4225352112676056,
    "predict_broadcastprogram_recall": 0.4462809917355372,
    "predict_car_f1": 0.5929443690637719,
    "predict_car_number": 688,
    "predict_car_precision": 0.5559796437659033,
    "predict_car_recall": 0.6351744186046512,
    "predict_chemicalthing_f1": 0.45660222130810363,
    "predict_chemicalthing_number": 1014,
    "predict_chemicalthing_precision": 0.3916725476358504,
    "predict_chemicalthing_recall": 0.5473372781065089,
    "predict_company_f1": 0.5705298814420517,
    "predict_company_number": 3903,
    "predict_company_precision": 0.5404538161815264,
    "predict_company_recall": 0.6041506533435819,
    "predict_currency_f1": 0.6302959953569355,
    "predict_currency_number": 799,
    "predict_currency_precision": 0.5876623376623377,
    "predict_currency_recall": 0.6795994993742178,
    "predict_director_f1": 0.49078014184397156,
    "predict_director_number": 554,
    "predict_director_precision": 0.40420560747663553,
    "predict_director_recall": 0.6245487364620939,
    "predict_disaster_f1": 0.3990929705215419,
    "predict_disaster_number": 207,
    "predict_disaster_precision": 0.37606837606837606,
    "predict_disaster_recall": 0.4251207729468599,
    "predict_disease_f1": 0.5335608646188852,
    "predict_disease_number": 750,
    "predict_disease_precision": 0.4652777777777778,
    "predict_disease_recall": 0.6253333333333333,
    "predict_education_f1": 0.6582390774007542,
    "predict_education_number": 2082,
    "predict_education_precision": 0.611454470539761,
    "predict_education_recall": 0.712776176753122,
    "predict_educationaldegree_f1": 0.4444444444444444,
    "predict_educationaldegree_number": 367,
    "predict_educationaldegree_precision": 0.3678571428571429,
    "predict_educationaldegree_recall": 0.5613079019073569,
    "predict_election_f1": 0.14035087719298245,
    "predict_election_number": 184,
    "predict_election_precision": 0.13023255813953488,
    "predict_election_recall": 0.15217391304347827,
    "predict_film_f1": 0.5505984766050055,
    "predict_film_number": 759,
    "predict_film_precision": 0.468952734012975,
    "predict_film_recall": 0.6666666666666666,
    "predict_food_f1": 0.4014084507042254,
    "predict_food_number": 432,
    "predict_food_precision": 0.32386363636363635,
    "predict_food_recall": 0.5277777777777778,
    "predict_game_f1": 0.5305719921104537,
    "predict_game_number": 496,
    "predict_game_precision": 0.5193050193050193,
    "predict_game_recall": 0.5423387096774194,
    "predict_god_f1": 0.5254491017964071,
    "predict_god_number": 635,
    "predict_god_precision": 0.5007132667617689,
    "predict_god_recall": 0.552755905511811,
    "predict_government/governmentagency_f1": 0.32385730211817165,
    "predict_government/governmentagency_number": 1535,
    "predict_government/governmentagency_precision": 0.2830004870920604,
    "predict_government/governmentagency_recall": 0.3785016286644951,
    "predict_hospital_f1": 0.6088082901554404,
    "predict_hospital_number": 364,
    "predict_hospital_precision": 0.5759803921568627,
    "predict_hospital_recall": 0.6456043956043956,
    "predict_hotel_f1": 0.548440065681445,
    "predict_hotel_number": 265,
    "predict_hotel_precision": 0.48546511627906974,
    "predict_hotel_recall": 0.630188679245283,
    "predict_island_f1": 0.48101265822784817,
    "predict_island_number": 646,
    "predict_island_precision": 0.4634146341463415,
    "predict_island_recall": 0.5,
    "predict_language_f1": 0.6299401197604791,
    "predict_language_number": 753,
    "predict_language_precision": 0.5736095965103599,
    "predict_language_recall": 0.6985391766268261,
    "predict_law_f1": 0.4330708661417323,
    "predict_law_number": 488,
    "predict_law_precision": 0.3516624040920716,
    "predict_law_recall": 0.5635245901639344,
    "predict_library_f1": 0.53836784409257,
    "predict_library_number": 357,
    "predict_library_precision": 0.47629310344827586,
    "predict_library_recall": 0.6190476190476191,
    "predict_livingthing_f1": 0.5302472382956339,
    "predict_livingthing_number": 865,
    "predict_livingthing_precision": 0.4864864864864865,
    "predict_livingthing_recall": 0.5826589595375723,
    "predict_loss": 0.5233648419380188,
    "predict_media/newspaper_f1": 0.5345160046278443,
    "predict_media/newspaper_number": 1234,
    "predict_media/newspaper_precision": 0.5099337748344371,
    "predict_media/newspaper_recall": 0.5615883306320908,
    "predict_medical_f1": 0.31858407079646023,
    "predict_medical_number": 397,
    "predict_medical_precision": 0.3197969543147208,
    "predict_medical_recall": 0.31738035264483627,
    "predict_mountain_f1": 0.5508982035928144,
    "predict_mountain_number": 681,
    "predict_mountain_precision": 0.5036496350364964,
    "predict_mountain_recall": 0.6079295154185022,
    "predict_music_f1": 0.6245019920318724,
    "predict_music_number": 1041,
    "predict_music_precision": 0.6483971044467425,
    "predict_music_recall": 0.6023054755043228,
    "predict_other_f1": 0.44259545058042005,
    "predict_other_number": 21035,
    "predict_other_precision": 0.4179268395708372,
    "predict_other_recall": 0.47035892560019016,
    "predict_overall_accuracy": 0.9006160333704647,
    "predict_overall_f1": 0.5628918789369459,
    "predict_overall_precision": 0.530156413881162,
    "predict_overall_recall": 0.5999360112289972,
    "predict_painting_f1": 0.0,
    "predict_painting_number": 58,
    "predict_painting_precision": 0.0,
    "predict_painting_recall": 0.0,
    "predict_park_f1": 0.4177215189873418,
    "predict_park_number": 458,
    "predict_park_precision": 0.32754342431761785,
    "predict_park_recall": 0.5764192139737991,
    "predict_politicalparty_f1": 0.5728856778580534,
    "predict_politicalparty_number": 1057,
    "predict_politicalparty_precision": 0.5200617283950617,
    "predict_politicalparty_recall": 0.6376537369914853,
    "predict_politician_f1": 0.5520120220404074,
    "predict_politician_number": 2859,
    "predict_politician_precision": 0.5281150159744409,
    "predict_politician_recall": 0.5781741867785939,
    "predict_protest_f1": 0.145985401459854,
    "predict_protest_number": 166,
    "predict_protest_precision": 0.12244897959183673,
    "predict_protest_recall": 0.18072289156626506,
    "predict_religion_f1": 0.41722745625841184,
    "predict_religion_number": 676,
    "predict_religion_precision": 0.38271604938271603,
    "predict_religion_recall": 0.45857988165680474,
    "predict_restaurant_f1": 0.28436018957345965,
    "predict_restaurant_number": 232,
    "predict_restaurant_precision": 0.3157894736842105,
    "predict_restaurant_recall": 0.25862068965517243,
    "predict_road/railway/highway/transit_f1": 0.5723124516627996,
    "predict_road/railway/highway/transit_number": 1702,
    "predict_road/railway/highway/transit_precision": 0.5098759761139182,
    "predict_road/railway/highway/transit_recall": 0.6521739130434783,
    "predict_runtime": 278.396,
    "predict_samples_per_second": 135.228,
    "predict_scholar_f1": 0.2888283378746594,
    "predict_scholar_number": 743,
    "predict_scholar_precision": 0.2924137931034483,
    "predict_scholar_recall": 0.2853297442799462,
    "predict_ship_f1": 0.46352941176470586,
    "predict_ship_number": 380,
    "predict_ship_precision": 0.41914893617021276,
    "predict_ship_recall": 0.5184210526315789,
    "predict_showorganization_f1": 0.4382955174322081,
    "predict_showorganization_number": 770,
    "predict_showorganization_precision": 0.381870781099325,
    "predict_showorganization_recall": 0.5142857142857142,
    "predict_software_f1": 0.5132119788608338,
    "predict_software_number": 889,
    "predict_software_precision": 0.5368550368550369,
    "predict_software_recall": 0.4915635545556805,
    "predict_soldier_f1": 0.397037037037037,
    "predict_soldier_number": 647,
    "predict_soldier_precision": 0.3812233285917496,
    "predict_soldier_recall": 0.4142194744976816,
    "predict_sportsevent_f1": 0.41825534373194684,
    "predict_sportsevent_number": 1572,
    "predict_sportsevent_precision": 0.38306878306878306,
    "predict_sportsevent_recall": 0.46055979643765904,
    "predict_sportsfacility_f1": 0.5825641025641026,
    "predict_sportsfacility_number": 420,
    "predict_sportsfacility_precision": 0.5117117117117117,
    "predict_sportsfacility_recall": 0.6761904761904762,
    "predict_sportsleague_f1": 0.48648648648648646,
    "predict_sportsleague_number": 885,
    "predict_sportsleague_precision": 0.4366576819407008,
    "predict_sportsleague_recall": 0.5491525423728814,
    "predict_sportsteam_f1": 0.6262395118230359,
    "predict_sportsteam_number": 2477,
    "predict_sportsteam_precision": 0.5934224792193712,
    "predict_sportsteam_recall": 0.6628986677432378,
    "predict_steps_per_second": 4.228,
    "predict_theater_f1": 0.5740570377184913,
    "predict_theater_number": 456,
    "predict_theater_precision": 0.49445324881141045,
    "predict_theater_recall": 0.6842105263157895,
    "predict_train_f1": 0.40161725067385445,
    "predict_train_number": 314,
    "predict_train_precision": 0.34813084112149534,
    "predict_train_recall": 0.4745222929936306,
    "predict_weapon_f1": 0.4000000000000001,
    "predict_weapon_number": 625,
    "predict_weapon_precision": 0.4358490566037736,
    "predict_weapon_recall": 0.3696,
    "predict_writtenart_f1": 0.46414253897550106,
    "predict_writtenart_number": 1032,
    "predict_writtenart_precision": 0.4295136026380874,
    "predict_writtenart_recall": 0.5048449612403101
}