{
    "predict_GPE_f1": 0.7499645975926362,
    "predict_GPE_number": 20409,
    "predict_GPE_precision": 0.723464323118255,
    "predict_GPE_recall": 0.778480082316625,
    "predict_actor_f1": 0.6899408284023669,
    "predict_actor_number": 1638,
    "predict_actor_precision": 0.669345579793341,
    "predict_actor_recall": 0.7118437118437119,
    "predict_airplane_f1": 0.5214446952595937,
    "predict_airplane_number": 794,
    "predict_airplane_precision": 0.4723926380368098,
    "predict_airplane_recall": 0.5818639798488665,
    "predict_airport_f1": 0.6254635352286775,
    "predict_airport_number": 364,
    "predict_airport_precision": 0.5685393258426966,
    "predict_airport_recall": 0.695054945054945,
    "predict_artist/author_f1": 0.5763206795858774,
    "predict_artist/author_number": 3464,
    "predict_artist/author_precision": 0.5334152334152334,
    "predict_artist/author_recall": 0.6267321016166282,
    "predict_astronomything_f1": 0.6470588235294117,
    "predict_astronomything_number": 678,
    "predict_astronomything_precision": 0.616,
    "predict_astronomything_recall": 0.6814159292035398,
    "predict_athlete_f1": 0.7813620071684589,
    "predict_athlete_number": 2907,
    "predict_athlete_precision": 0.7421850820179511,
    "predict_athlete_recall": 0.824905400756794,
    "predict_attack/battle/war/militaryconflict_f1": 0.6045513095749249,
    "predict_attack/battle/war/militaryconflict_number": 1099,
    "predict_attack/battle/war/militaryconflict_precision": 0.5723577235772358,
    "predict_attack/battle/war/militaryconflict_recall": 0.640582347588717,
    "predict_award_f1": 0.4431192660550458,
    "predict_award_number": 941,
    "predict_award_precision": 0.3898305084745763,
    "predict_award_recall": 0.5132837407013815,
    "predict_biologything_f1": 0.5578757411704047,
    "predict_biologything_number": 1875,
    "predict_biologything_precision": 0.5399201596806387,
    "predict_biologything_recall": 0.5770666666666666,
    "predict_bodiesofwater_f1": 0.5948632974316488,
    "predict_bodiesofwater_number": 1169,
    "predict_bodiesofwater_precision": 0.576706827309237,
    "predict_bodiesofwater_recall": 0.6142001710863987,
    "predict_broadcastprogram_f1": 0.43571978444957654,
    "predict_broadcastprogram_number": 605,
    "predict_broadcastprogram_precision": 0.40778097982708933,
    "predict_broadcastprogram_recall": 0.4677685950413223,
    "predict_car_f1": 0.5782957028404954,
    "predict_car_number": 688,
    "predict_car_precision": 0.5795620437956205,
    "predict_car_recall": 0.5770348837209303,
    "predict_chemicalthing_f1": 0.4857928505957837,
    "predict_chemicalthing_number": 1014,
    "predict_chemicalthing_precision": 0.4537671232876712,
    "predict_chemicalthing_recall": 0.5226824457593688,
    "predict_company_f1": 0.5397131493310836,
    "predict_company_number": 3903,
    "predict_company_precision": 0.5095584888484297,
    "predict_company_recall": 0.5736612861901101,
    "predict_currency_f1": 0.644789867587795,
    "predict_currency_number": 799,
    "predict_currency_precision": 0.5970149253731343,
    "predict_currency_recall": 0.7008760951188986,
    "predict_director_f1": 0.5979381443298968,
    "predict_director_number": 554,
    "predict_director_precision": 0.621832358674464,
    "predict_director_recall": 0.575812274368231,
    "predict_disaster_f1": 0.3556485355648536,
    "predict_disaster_number": 207,
    "predict_disaster_precision": 0.31365313653136534,
    "predict_disaster_recall": 0.4106280193236715,
    "predict_disease_f1": 0.52329360780065,
    "predict_disease_number": 750,
    "predict_disease_precision": 0.4406934306569343,
    "predict_disease_recall": 0.644,
    "predict_education_f1": 0.6119831969931461,
    "predict_education_number": 2082,
    "predict_education_precision": 0.5669807455960671,
    "predict_education_recall": 0.664745437079731,
    "predict_educationaldegree_f1": 0.43661971830985913,
    "predict_educationaldegree_number": 367,
    "predict_educationaldegree_precision": 0.34609250398724084,
    "predict_educationaldegree_recall": 0.5912806539509536,
    "predict_election_f1": 0.16826923076923075,
    "predict_election_number": 184,
    "predict_election_precision": 0.15086206896551724,
    "predict_election_recall": 0.19021739130434784,
    "predict_film_f1": 0.5788519637462236,
    "predict_film_number": 759,
    "predict_film_precision": 0.5345982142857143,
    "predict_film_recall": 0.6310935441370223,
    "predict_food_f1": 0.4109347442680776,
    "predict_food_number": 432,
    "predict_food_precision": 0.3319088319088319,
    "predict_food_recall": 0.5393518518518519,
    "predict_game_f1": 0.5182987141444114,
    "predict_game_number": 496,
    "predict_game_precision": 0.5087378640776699,
    "predict_game_recall": 0.5282258064516129,
    "predict_god_f1": 0.5691527878349022,
    "predict_god_number": 635,
    "predict_god_precision": 0.5268096514745308,
    "predict_god_recall": 0.6188976377952756,
    "predict_government/governmentagency_f1": 0.28562874251497006,
    "predict_government/governmentagency_number": 1535,
    "predict_government/governmentagency_precision": 0.2642659279778393,
    "predict_government/governmentagency_recall": 0.31074918566775245,
    "predict_hospital_f1": 0.555417185554172,
    "predict_hospital_number": 364,
    "predict_hospital_precision": 0.5079726651480638,
    "predict_hospital_recall": 0.6126373626373627,
    "predict_hotel_f1": 0.43661971830985913,
    "predict_hotel_number": 265,
    "predict_hotel_precision": 0.34831460674157305,
    "predict_hotel_recall": 0.5849056603773585,
    "predict_island_f1": 0.5761865112406328,
    "predict_island_number": 646,
    "predict_island_precision": 0.6234234234234234,
    "predict_island_recall": 0.5356037151702786,
    "predict_language_f1": 0.6297169811320754,
    "predict_language_number": 753,
    "predict_language_precision": 0.5662778366914104,
    "predict_language_recall": 0.7091633466135459,
    "predict_law_f1": 0.46153846153846156,
    "predict_law_number": 488,
    "predict_law_precision": 0.4095238095238095,
    "predict_law_recall": 0.5286885245901639,
    "predict_library_f1": 0.4834905660377358,
    "predict_library_number": 357,
    "predict_library_precision": 0.4175152749490835,
    "predict_library_recall": 0.5742296918767507,
    "predict_livingthing_f1": 0.506060606060606,
    "predict_livingthing_number": 865,
    "predict_livingthing_precision": 0.4493273542600897,
    "predict_livingthing_recall": 0.5791907514450867,
    "predict_loss": 0.6171633005142212,
    "predict_media/newspaper_f1": 0.49666913397483353,
    "predict_media/newspaper_number": 1234,
    "predict_media/newspaper_precision": 0.45708446866485014,
    "predict_media/newspaper_recall": 0.5437601296596435,
    "predict_medical_f1": 0.40139211136890957,
    "predict_medical_number": 397,
    "predict_medical_precision": 0.3720430107526882,
    "predict_medical_recall": 0.4357682619647355,
    "predict_mountain_f1": 0.5699326851159313,
    "predict_mountain_number": 681,
    "predict_mountain_precision": 0.5807926829268293,
    "predict_mountain_recall": 0.5594713656387665,
    "predict_music_f1": 0.5940246045694201,
    "predict_music_number": 1041,
    "predict_music_precision": 0.5473684210526316,
    "predict_music_recall": 0.6493756003842459,
    "predict_other_f1": 0.4540554694830558,
    "predict_other_number": 21035,
    "predict_other_precision": 0.4196515004840271,
    "predict_other_recall": 0.49460423104349893,
    "predict_overall_accuracy": 0.9023477450833501,
    "predict_overall_f1": 0.5625540418500088,
    "predict_overall_precision": 0.5261861969805895,
    "predict_overall_recall": 0.6043223382735416,
    "predict_painting_f1": 0.26666666666666666,
    "predict_painting_number": 58,
    "predict_painting_precision": 0.23376623376623376,
    "predict_painting_recall": 0.3103448275862069,
    "predict_park_f1": 0.410958904109589,
    "predict_park_number": 458,
    "predict_park_precision": 0.3532182103610675,
    "predict_park_recall": 0.4912663755458515,
    "predict_politicalparty_f1": 0.5797849462365592,
    "predict_politicalparty_number": 1057,
    "predict_politicalparty_precision": 0.5315457413249212,
    "predict_politicalparty_recall": 0.6376537369914853,
    "predict_politician_f1": 0.5246449456975774,
    "predict_politician_number": 2859,
    "predict_politician_precision": 0.5022392834293026,
    "predict_politician_recall": 0.5491430570129416,
    "predict_protest_f1": 0.23437499999999997,
    "predict_protest_number": 166,
    "predict_protest_precision": 0.20642201834862386,
    "predict_protest_recall": 0.2710843373493976,
    "predict_religion_f1": 0.43236245954692554,
    "predict_religion_number": 676,
    "predict_religion_precision": 0.38434982738780205,
    "predict_religion_recall": 0.4940828402366864,
    "predict_restaurant_f1": 0.24460431654676262,
    "predict_restaurant_number": 232,
    "predict_restaurant_precision": 0.2756756756756757,
    "predict_restaurant_recall": 0.21982758620689655,
    "predict_road/railway/highway/transit_f1": 0.5472847682119205,
    "predict_road/railway/highway/transit_number": 1702,
    "predict_road/railway/highway/transit_precision": 0.4983116256632899,
    "predict_road/railway/highway/transit_recall": 0.6069330199764983,
    "predict_runtime": 269.6546,
    "predict_samples_per_second": 139.612,
    "predict_scholar_f1": 0.337992376111817,
    "predict_scholar_number": 743,
    "predict_scholar_precision": 0.3200962695547533,
    "predict_scholar_recall": 0.35800807537012114,
    "predict_ship_f1": 0.47677261613691935,
    "predict_ship_number": 380,
    "predict_ship_precision": 0.4452054794520548,
    "predict_ship_recall": 0.5131578947368421,
    "predict_showorganization_f1": 0.39081885856079407,
    "predict_showorganization_number": 770,
    "predict_showorganization_precision": 0.37410926365795727,
    "predict_showorganization_recall": 0.4090909090909091,
    "predict_software_f1": 0.45947456679709336,
    "predict_software_number": 889,
    "predict_software_precision": 0.45666666666666667,
    "predict_software_recall": 0.46231721034870643,
    "predict_soldier_f1": 0.3964886613021214,
    "predict_soldier_number": 647,
    "predict_soldier_precision": 0.3763888888888889,
    "predict_soldier_recall": 0.4188562596599691,
    "predict_sportsevent_f1": 0.4569631112382042,
    "predict_sportsevent_number": 1572,
    "predict_sportsevent_precision": 0.4150649350649351,
    "predict_sportsevent_recall": 0.5082697201017812,
    "predict_sportsfacility_f1": 0.5271629778672032,
    "predict_sportsfacility_number": 420,
    "predict_sportsfacility_precision": 0.4564459930313589,
    "predict_sportsfacility_recall": 0.6238095238095238,
    "predict_sportsleague_f1": 0.48423194303153616,
    "predict_sportsleague_number": 885,
    "predict_sportsleague_precision": 0.44033302497687327,
    "predict_sportsleague_recall": 0.5378531073446328,
    "predict_sportsteam_f1": 0.6380484114977307,
    "predict_sportsteam_number": 2477,
    "predict_sportsteam_precision": 0.60014229811455,
    "predict_sportsteam_recall": 0.6810658054097699,
    "predict_steps_per_second": 4.365,
    "predict_theater_f1": 0.5813221406086044,
    "predict_theater_number": 456,
    "predict_theater_precision": 0.5573440643863179,
    "predict_theater_recall": 0.6074561403508771,
    "predict_train_f1": 0.39840637450199207,
    "predict_train_number": 314,
    "predict_train_precision": 0.3416856492027335,
    "predict_train_recall": 0.47770700636942676,
    "predict_weapon_f1": 0.41673502871205903,
    "predict_weapon_number": 625,
    "predict_weapon_precision": 0.4276094276094276,
    "predict_weapon_recall": 0.4064,
    "predict_writtenart_f1": 0.46794055201698515,
    "predict_writtenart_number": 1032,
    "predict_writtenart_precision": 0.41647770219198793,
    "predict_writtenart_recall": 0.5339147286821705
}