{
    "predict_GPE_f1": 0.7642867390368706,
    "predict_GPE_number": 20409,
    "predict_GPE_precision": 0.7463690281604632,
    "predict_GPE_recall": 0.7830858934783674,
    "predict_actor_f1": 0.644199611147116,
    "predict_actor_number": 1638,
    "predict_actor_precision": 0.68646408839779,
    "predict_actor_recall": 0.6068376068376068,
    "predict_airplane_f1": 0.5184776613348042,
    "predict_airplane_number": 794,
    "predict_airplane_precision": 0.46123650637880276,
    "predict_airplane_recall": 0.5919395465994962,
    "predict_airport_f1": 0.5722772277227723,
    "predict_airport_number": 364,
    "predict_airport_precision": 0.4473684210526316,
    "predict_airport_recall": 0.7939560439560439,
    "predict_artist/author_f1": 0.5464976651100735,
    "predict_artist/author_number": 3464,
    "predict_artist/author_precision": 0.5080625155048375,
    "predict_artist/author_recall": 0.5912240184757506,
    "predict_astronomything_f1": 0.5425219941348974,
    "predict_astronomything_number": 678,
    "predict_astronomything_precision": 0.5393586005830904,
    "predict_astronomything_recall": 0.5457227138643068,
    "predict_athlete_f1": 0.7553691275167785,
    "predict_athlete_number": 2907,
    "predict_athlete_precision": 0.7373075663282017,
    "predict_athlete_recall": 0.7743378052975576,
    "predict_attack/battle/war/militaryconflict_f1": 0.6066144473455178,
    "predict_attack/battle/war/militaryconflict_number": 1099,
    "predict_attack/battle/war/militaryconflict_precision": 0.5813177648040033,
    "predict_attack/battle/war/militaryconflict_recall": 0.6342129208371247,
    "predict_award_f1": 0.4005486968449931,
    "predict_award_number": 941,
    "predict_award_precision": 0.35152487961476725,
    "predict_award_recall": 0.46546227417640806,
    "predict_biologything_f1": 0.5078338721711018,
    "predict_biologything_number": 1875,
    "predict_biologything_precision": 0.47576887232059645,
    "predict_biologything_recall": 0.5445333333333333,
    "predict_bodiesofwater_f1": 0.6346386758175212,
    "predict_bodiesofwater_number": 1169,
    "predict_bodiesofwater_precision": 0.6009174311926605,
    "predict_bodiesofwater_recall": 0.6723695466210436,
    "predict_broadcastprogram_f1": 0.3728251864125932,
    "predict_broadcastprogram_number": 605,
    "predict_broadcastprogram_precision": 0.37375415282392027,
    "predict_broadcastprogram_recall": 0.371900826446281,
    "predict_car_f1": 0.5663841807909605,
    "predict_car_number": 688,
    "predict_car_precision": 0.5508241758241759,
    "predict_car_recall": 0.5828488372093024,
    "predict_chemicalthing_f1": 0.4559748427672956,
    "predict_chemicalthing_number": 1014,
    "predict_chemicalthing_precision": 0.3790849673202614,
    "predict_chemicalthing_recall": 0.571992110453649,
    "predict_company_f1": 0.5658958879143411,
    "predict_company_number": 3903,
    "predict_company_precision": 0.5094339622641509,
    "predict_company_recall": 0.6364335126825519,
    "predict_currency_f1": 0.5913660555884093,
    "predict_currency_number": 799,
    "predict_currency_precision": 0.5605381165919282,
    "predict_currency_recall": 0.6257822277847309,
    "predict_director_f1": 0.4257950530035336,
    "predict_director_number": 554,
    "predict_director_precision": 0.41695501730103807,
    "predict_director_recall": 0.43501805054151627,
    "predict_disaster_f1": 0.3794642857142857,
    "predict_disaster_number": 207,
    "predict_disaster_precision": 0.35269709543568467,
    "predict_disaster_recall": 0.4106280193236715,
    "predict_disease_f1": 0.49789915966386555,
    "predict_disease_number": 750,
    "predict_disease_precision": 0.41074523396880414,
    "predict_disease_recall": 0.632,
    "predict_education_f1": 0.6672669968482666,
    "predict_education_number": 2082,
    "predict_education_precision": 0.6279661016949153,
    "predict_education_recall": 0.7118155619596542,
    "predict_educationaldegree_f1": 0.4550155118924508,
    "predict_educationaldegree_number": 367,
    "predict_educationaldegree_precision": 0.36666666666666664,
    "predict_educationaldegree_recall": 0.5994550408719346,
    "predict_election_f1": 0.18181818181818182,
    "predict_election_number": 184,
    "predict_election_precision": 0.13527851458885942,
    "predict_election_recall": 0.27717391304347827,
    "predict_film_f1": 0.5355450236966824,
    "predict_film_number": 759,
    "predict_film_precision": 0.4865446716899892,
    "predict_film_recall": 0.5955204216073782,
    "predict_food_f1": 0.39850560398505597,
    "predict_food_number": 432,
    "predict_food_precision": 0.431266846361186,
    "predict_food_recall": 0.37037037037037035,
    "predict_game_f1": 0.5159914712153518,
    "predict_game_number": 496,
    "predict_game_precision": 0.5475113122171946,
    "predict_game_recall": 0.4879032258064516,
    "predict_god_f1": 0.563467492260062,
    "predict_god_number": 635,
    "predict_god_precision": 0.5540334855403348,
    "predict_god_recall": 0.573228346456693,
    "predict_government/governmentagency_f1": 0.3203463203463203,
    "predict_government/governmentagency_number": 1535,
    "predict_government/governmentagency_precision": 0.28756476683937826,
    "predict_government/governmentagency_recall": 0.36156351791530944,
    "predict_hospital_f1": 0.6572890025575449,
    "predict_hospital_number": 364,
    "predict_hospital_precision": 0.6148325358851675,
    "predict_hospital_recall": 0.7060439560439561,
    "predict_hotel_f1": 0.5382262996941896,
    "predict_hotel_number": 265,
    "predict_hotel_precision": 0.4524421593830334,
    "predict_hotel_recall": 0.6641509433962264,
    "predict_island_f1": 0.4886095836606441,
    "predict_island_number": 646,
    "predict_island_precision": 0.4960127591706539,
    "predict_island_recall": 0.48142414860681115,
    "predict_language_f1": 0.5867136978248089,
    "predict_language_number": 753,
    "predict_language_precision": 0.5263713080168776,
    "predict_language_recall": 0.6626826029216467,
    "predict_law_f1": 0.3899159663865546,
    "predict_law_number": 488,
    "predict_law_precision": 0.33048433048433046,
    "predict_law_recall": 0.47540983606557374,
    "predict_library_f1": 0.5287958115183246,
    "predict_library_number": 357,
    "predict_library_precision": 0.4963144963144963,
    "predict_library_recall": 0.5658263305322129,
    "predict_livingthing_f1": 0.49638286032276013,
    "predict_livingthing_number": 865,
    "predict_livingthing_precision": 0.47854077253218885,
    "predict_livingthing_recall": 0.5156069364161849,
    "predict_loss": 0.5113760828971863,
    "predict_media/newspaper_f1": 0.5238095238095238,
    "predict_media/newspaper_number": 1234,
    "predict_media/newspaper_precision": 0.5132192846034215,
    "predict_media/newspaper_recall": 0.5348460291734197,
    "predict_medical_f1": 0.327007299270073,
    "predict_medical_number": 397,
    "predict_medical_precision": 0.3888888888888889,
    "predict_medical_recall": 0.28211586901763225,
    "predict_mountain_f1": 0.5886026541764247,
    "predict_mountain_number": 681,
    "predict_mountain_precision": 0.6283333333333333,
    "predict_mountain_recall": 0.55359765051395,
    "predict_music_f1": 0.6198775317946303,
    "predict_music_number": 1041,
    "predict_music_precision": 0.6081330868761553,
    "predict_music_recall": 0.6320845341018252,
    "predict_other_f1": 0.4416616709962477,
    "predict_other_number": 21035,
    "predict_other_precision": 0.41434760873187804,
    "predict_other_recall": 0.47283099595911576,
    "predict_overall_accuracy": 0.8983143225044351,
    "predict_overall_f1": 0.5540255937586638,
    "predict_overall_precision": 0.5239225426613311,
    "predict_overall_recall": 0.5877987862775048,
    "predict_painting_f1": 0.05128205128205129,
    "predict_painting_number": 58,
    "predict_painting_precision": 0.1,
    "predict_painting_recall": 0.034482758620689655,
    "predict_park_f1": 0.3903420523138833,
    "predict_park_number": 458,
    "predict_park_precision": 0.3619402985074627,
    "predict_park_recall": 0.42358078602620086,
    "predict_politicalparty_f1": 0.5770750988142292,
    "predict_politicalparty_number": 1057,
    "predict_politicalparty_precision": 0.5385245901639344,
    "predict_politicalparty_recall": 0.6215704824976348,
    "predict_politician_f1": 0.5110041265474553,
    "predict_politician_number": 2859,
    "predict_politician_precision": 0.5025363544132567,
    "predict_politician_recall": 0.5197621545995104,
    "predict_protest_f1": 0.13513513513513514,
    "predict_protest_number": 166,
    "predict_protest_precision": 0.26785714285714285,
    "predict_protest_recall": 0.09036144578313253,
    "predict_religion_f1": 0.40239043824701193,
    "predict_religion_number": 676,
    "predict_religion_precision": 0.3650602409638554,
    "predict_religion_recall": 0.44822485207100593,
    "predict_restaurant_f1": 0.23370786516853934,
    "predict_restaurant_number": 232,
    "predict_restaurant_precision": 0.24413145539906103,
    "predict_restaurant_recall": 0.22413793103448276,
    "predict_road/railway/highway/transit_f1": 0.5532144786601836,
    "predict_road/railway/highway/transit_number": 1702,
    "predict_road/railway/highway/transit_precision": 0.512,
    "predict_road/railway/highway/transit_recall": 0.6016451233842538,
    "predict_runtime": 280.8503,
    "predict_samples_per_second": 134.047,
    "predict_scholar_f1": 0.1681877444589309,
    "predict_scholar_number": 743,
    "predict_scholar_precision": 0.16308470290771176,
    "predict_scholar_recall": 0.17362045760430686,
    "predict_ship_f1": 0.4142011834319526,
    "predict_ship_number": 380,
    "predict_ship_precision": 0.47297297297297297,
    "predict_ship_recall": 0.3684210526315789,
    "predict_showorganization_f1": 0.40629095674967236,
    "predict_showorganization_number": 770,
    "predict_showorganization_precision": 0.41005291005291006,
    "predict_showorganization_recall": 0.4025974025974026,
    "predict_software_f1": 0.48332527791203483,
    "predict_software_number": 889,
    "predict_software_precision": 0.423728813559322,
    "predict_software_recall": 0.562429696287964,
    "predict_soldier_f1": 0.28620394173093405,
    "predict_soldier_number": 647,
    "predict_soldier_precision": 0.3211538461538462,
    "predict_soldier_recall": 0.2581143740340031,
    "predict_sportsevent_f1": 0.41910112359550566,
    "predict_sportsevent_number": 1572,
    "predict_sportsevent_precision": 0.37525150905432597,
    "predict_sportsevent_recall": 0.47455470737913485,
    "predict_sportsfacility_f1": 0.5802238805970149,
    "predict_sportsfacility_number": 420,
    "predict_sportsfacility_precision": 0.47699386503067487,
    "predict_sportsfacility_recall": 0.7404761904761905,
    "predict_sportsleague_f1": 0.4460093896713615,
    "predict_sportsleague_number": 885,
    "predict_sportsleague_precision": 0.3815261044176707,
    "predict_sportsleague_recall": 0.536723163841808,
    "predict_sportsteam_f1": 0.6503496503496503,
    "predict_sportsteam_number": 2477,
    "predict_sportsteam_precision": 0.6267315612130289,
    "predict_sportsteam_recall": 0.6758175211949939,
    "predict_steps_per_second": 4.191,
    "predict_theater_f1": 0.5867924528301888,
    "predict_theater_number": 456,
    "predict_theater_precision": 0.5149006622516556,
    "predict_theater_recall": 0.6820175438596491,
    "predict_train_f1": 0.3197389885807504,
    "predict_train_number": 314,
    "predict_train_precision": 0.3277591973244147,
    "predict_train_recall": 0.31210191082802546,
    "predict_weapon_f1": 0.3712784588441331,
    "predict_weapon_number": 625,
    "predict_weapon_precision": 0.41005802707930367,
    "predict_weapon_recall": 0.3392,
    "predict_writtenart_f1": 0.3650156180276662,
    "predict_writtenart_number": 1032,
    "predict_writtenart_precision": 0.33829611248966085,
    "predict_writtenart_recall": 0.3963178294573643
}