{
    "predict_GPE_f1": 0.7553850552802135,
    "predict_GPE_number": 20409,
    "predict_GPE_precision": 0.7352381835892203,
    "predict_GPE_recall": 0.7766671566465775,
    "predict_actor_f1": 0.7055900621118013,
    "predict_actor_number": 1638,
    "predict_actor_precision": 0.718078381795196,
    "predict_actor_recall": 0.6935286935286935,
    "predict_airplane_f1": 0.530018192844148,
    "predict_airplane_number": 794,
    "predict_airplane_precision": 0.5111111111111111,
    "predict_airplane_recall": 0.5503778337531486,
    "predict_airport_f1": 0.636568848758465,
    "predict_airport_number": 364,
    "predict_airport_precision": 0.5402298850574713,
    "predict_airport_recall": 0.7747252747252747,
    "predict_artist/author_f1": 0.5885444035733052,
    "predict_artist/author_number": 3464,
    "predict_artist/author_precision": 0.5400192864030858,
    "predict_artist/author_recall": 0.6466512702078522,
    "predict_astronomything_f1": 0.6616746085772635,
    "predict_astronomything_number": 678,
    "predict_astronomything_precision": 0.6144121365360303,
    "predict_astronomything_recall": 0.7168141592920354,
    "predict_athlete_f1": 0.7696990192762936,
    "predict_athlete_number": 2907,
    "predict_athlete_precision": 0.7569005653475225,
    "predict_athlete_recall": 0.782937736498108,
    "predict_attack/battle/war/militaryconflict_f1": 0.6219723183391004,
    "predict_attack/battle/war/militaryconflict_number": 1099,
    "predict_attack/battle/war/militaryconflict_precision": 0.5927452596867271,
    "predict_attack/battle/war/militaryconflict_recall": 0.654231119199272,
    "predict_award_f1": 0.4499036608863199,
    "predict_award_number": 941,
    "predict_award_precision": 0.41145374449339206,
    "predict_award_recall": 0.4962805526036132,
    "predict_biologything_f1": 0.49673913043478257,
    "predict_biologything_number": 1875,
    "predict_biologything_precision": 0.506371191135734,
    "predict_biologything_recall": 0.48746666666666666,
    "predict_bodiesofwater_f1": 0.6103789126853377,
    "predict_bodiesofwater_number": 1169,
    "predict_bodiesofwater_precision": 0.5885623510722796,
    "predict_bodiesofwater_recall": 0.6338751069289992,
    "predict_broadcastprogram_f1": 0.42136498516320475,
    "predict_broadcastprogram_number": 605,
    "predict_broadcastprogram_precision": 0.3822341857335128,
    "predict_broadcastprogram_recall": 0.46942148760330576,
    "predict_car_f1": 0.5742574257425742,
    "predict_car_number": 688,
    "predict_car_precision": 0.5259975816203144,
    "predict_car_recall": 0.6322674418604651,
    "predict_chemicalthing_f1": 0.48073836276083465,
    "predict_chemicalthing_number": 1014,
    "predict_chemicalthing_precision": 0.40527740189445194,
    "predict_chemicalthing_recall": 0.5907297830374754,
    "predict_company_f1": 0.5551584465094114,
    "predict_company_number": 3903,
    "predict_company_precision": 0.5188154085949677,
    "predict_company_recall": 0.5969766846015885,
    "predict_currency_f1": 0.6320046216060081,
    "predict_currency_number": 799,
    "predict_currency_precision": 0.5869098712446352,
    "predict_currency_recall": 0.6846057571964956,
    "predict_director_f1": 0.5372168284789643,
    "predict_director_number": 554,
    "predict_director_precision": 0.4868035190615836,
    "predict_director_recall": 0.5992779783393501,
    "predict_disaster_f1": 0.37442922374429227,
    "predict_disaster_number": 207,
    "predict_disaster_precision": 0.354978354978355,
    "predict_disaster_recall": 0.3961352657004831,
    "predict_disease_f1": 0.5441527446300717,
    "predict_disease_number": 750,
    "predict_disease_precision": 0.4924406047516199,
    "predict_disease_recall": 0.608,
    "predict_education_f1": 0.671804170444243,
    "predict_education_number": 2082,
    "predict_education_precision": 0.6360515021459228,
    "predict_education_recall": 0.7118155619596542,
    "predict_educationaldegree_f1": 0.454337899543379,
    "predict_educationaldegree_number": 367,
    "predict_educationaldegree_precision": 0.39096267190569745,
    "predict_educationaldegree_recall": 0.5422343324250681,
    "predict_election_f1": 0.20915032679738563,
    "predict_election_number": 184,
    "predict_election_precision": 0.17454545454545456,
    "predict_election_recall": 0.2608695652173913,
    "predict_film_f1": 0.5970904490828589,
    "predict_film_number": 759,
    "predict_film_precision": 0.5742092457420924,
    "predict_film_recall": 0.621870882740448,
    "predict_food_f1": 0.40721102863202546,
    "predict_food_number": 432,
    "predict_food_precision": 0.37573385518590996,
    "predict_food_recall": 0.4444444444444444,
    "predict_game_f1": 0.5623800383877159,
    "predict_game_number": 496,
    "predict_game_precision": 0.5366300366300366,
    "predict_game_recall": 0.5907258064516129,
    "predict_god_f1": 0.5227272727272727,
    "predict_god_number": 635,
    "predict_god_precision": 0.4760672703751617,
    "predict_god_recall": 0.5795275590551181,
    "predict_government/governmentagency_f1": 0.32895941409826057,
    "predict_government/governmentagency_number": 1535,
    "predict_government/governmentagency_precision": 0.309414466130884,
    "predict_government/governmentagency_recall": 0.3511400651465798,
    "predict_hospital_f1": 0.6089108910891088,
    "predict_hospital_number": 364,
    "predict_hospital_precision": 0.5540540540540541,
    "predict_hospital_recall": 0.6758241758241759,
    "predict_hotel_f1": 0.5160075329566854,
    "predict_hotel_number": 265,
    "predict_hotel_precision": 0.5150375939849624,
    "predict_hotel_recall": 0.5169811320754717,
    "predict_island_f1": 0.5494327390599676,
    "predict_island_number": 646,
    "predict_island_precision": 0.576530612244898,
    "predict_island_recall": 0.5247678018575851,
    "predict_language_f1": 0.5993111366245695,
    "predict_language_number": 753,
    "predict_language_precision": 0.5278058645096056,
    "predict_language_recall": 0.6932270916334662,
    "predict_law_f1": 0.46977547495682204,
    "predict_law_number": 488,
    "predict_law_precision": 0.4059701492537313,
    "predict_law_recall": 0.5573770491803278,
    "predict_library_f1": 0.6055979643765903,
    "predict_library_number": 357,
    "predict_library_precision": 0.5547785547785548,
    "predict_library_recall": 0.6666666666666666,
    "predict_livingthing_f1": 0.5354590434304564,
    "predict_livingthing_number": 865,
    "predict_livingthing_precision": 0.510482180293501,
    "predict_livingthing_recall": 0.5630057803468208,
    "predict_loss": 0.6312606334686279,
    "predict_media/newspaper_f1": 0.5038539553752536,
    "predict_media/newspaper_number": 1234,
    "predict_media/newspaper_precision": 0.50446791226645,
    "predict_media/newspaper_recall": 0.5032414910858996,
    "predict_medical_f1": 0.4070796460176991,
    "predict_medical_number": 397,
    "predict_medical_precision": 0.4086294416243655,
    "predict_medical_recall": 0.40554156171284633,
    "predict_mountain_f1": 0.5567423230974633,
    "predict_mountain_number": 681,
    "predict_mountain_precision": 0.5104039167686658,
    "predict_mountain_recall": 0.6123348017621145,
    "predict_music_f1": 0.61134163208852,
    "predict_music_number": 1041,
    "predict_music_precision": 0.5877659574468085,
    "predict_music_recall": 0.6368876080691642,
    "predict_other_f1": 0.46458680852982287,
    "predict_other_number": 21035,
    "predict_other_precision": 0.4417627641788485,
    "predict_other_recall": 0.48989778939862133,
    "predict_overall_accuracy": 0.9024074592803462,
    "predict_overall_f1": 0.5726607180358774,
    "predict_overall_precision": 0.5435421514727288,
    "predict_overall_recall": 0.6050757544482517,
    "predict_painting_f1": 0.2797202797202797,
    "predict_painting_number": 58,
    "predict_painting_precision": 0.23529411764705882,
    "predict_painting_recall": 0.3448275862068966,
    "predict_park_f1": 0.47269303201506596,
    "predict_park_number": 458,
    "predict_park_precision": 0.4155629139072848,
    "predict_park_recall": 0.5480349344978166,
    "predict_politicalparty_f1": 0.5961871750433275,
    "predict_politicalparty_number": 1057,
    "predict_politicalparty_precision": 0.5499600319744204,
    "predict_politicalparty_recall": 0.6508987701040682,
    "predict_politician_f1": 0.5332849628151641,
    "predict_politician_number": 2859,
    "predict_politician_precision": 0.5538809344385832,
    "predict_politician_recall": 0.5141657922350472,
    "predict_protest_f1": 0.23364485981308414,
    "predict_protest_number": 166,
    "predict_protest_precision": 0.19083969465648856,
    "predict_protest_recall": 0.30120481927710846,
    "predict_religion_f1": 0.44238410596026495,
    "predict_religion_number": 676,
    "predict_religion_precision": 0.40047961630695444,
    "predict_religion_recall": 0.4940828402366864,
    "predict_restaurant_f1": 0.3140794223826715,
    "predict_restaurant_number": 232,
    "predict_restaurant_precision": 0.2701863354037267,
    "predict_restaurant_recall": 0.375,
    "predict_road/railway/highway/transit_f1": 0.594413407821229,
    "predict_road/railway/highway/transit_number": 1702,
    "predict_road/railway/highway/transit_precision": 0.5665601703940362,
    "predict_road/railway/highway/transit_recall": 0.6251468860164512,
    "predict_runtime": 285.2061,
    "predict_samples_per_second": 131.999,
    "predict_scholar_f1": 0.3273510409188801,
    "predict_scholar_number": 743,
    "predict_scholar_precision": 0.3507692307692308,
    "predict_scholar_recall": 0.30686406460296095,
    "predict_ship_f1": 0.5155666251556662,
    "predict_ship_number": 380,
    "predict_ship_precision": 0.48936170212765956,
    "predict_ship_recall": 0.5447368421052632,
    "predict_showorganization_f1": 0.42464917632702864,
    "predict_showorganization_number": 770,
    "predict_showorganization_precision": 0.4004602991944764,
    "predict_showorganization_recall": 0.45194805194805193,
    "predict_software_f1": 0.4863731656184486,
    "predict_software_number": 889,
    "predict_software_precision": 0.4553483807654563,
    "predict_software_recall": 0.5219347581552306,
    "predict_soldier_f1": 0.3248407643312101,
    "predict_soldier_number": 647,
    "predict_soldier_precision": 0.33497536945812806,
    "predict_soldier_recall": 0.31530139103554866,
    "predict_sportsevent_f1": 0.43167524299599774,
    "predict_sportsevent_number": 1572,
    "predict_sportsevent_precision": 0.3920041536863967,
    "predict_sportsevent_recall": 0.4802798982188295,
    "predict_sportsfacility_f1": 0.586171310629515,
    "predict_sportsfacility_number": 420,
    "predict_sportsfacility_precision": 0.517304189435337,
    "predict_sportsfacility_recall": 0.6761904761904762,
    "predict_sportsleague_f1": 0.47804878048780486,
    "predict_sportsleague_number": 885,
    "predict_sportsleague_precision": 0.4206008583690987,
    "predict_sportsleague_recall": 0.5536723163841808,
    "predict_sportsteam_f1": 0.6498482549317147,
    "predict_sportsteam_number": 2477,
    "predict_sportsteam_precision": 0.6128801431127012,
    "predict_sportsteam_recall": 0.6915623738393217,
    "predict_steps_per_second": 4.127,
    "predict_theater_f1": 0.6161048689138577,
    "predict_theater_number": 456,
    "predict_theater_precision": 0.5375816993464052,
    "predict_theater_recall": 0.7214912280701754,
    "predict_train_f1": 0.42077230359520634,
    "predict_train_number": 314,
    "predict_train_precision": 0.36155606407322655,
    "predict_train_recall": 0.5031847133757962,
    "predict_weapon_f1": 0.41634541249036233,
    "predict_weapon_number": 625,
    "predict_weapon_precision": 0.4017857142857143,
    "predict_weapon_recall": 0.432,
    "predict_writtenart_f1": 0.5098039215686274,
    "predict_writtenart_number": 1032,
    "predict_writtenart_precision": 0.4550989345509893,
    "predict_writtenart_recall": 0.5794573643410853
}